{
  "cycle": 2,
  "timestamp": "2026-03-26T00:27:57.153485",
  "date": "2026-03-26",
  "time": "00:27:57 ",
  "author": "Andrea Marro \u2014 ELAB Tutor \u00a9 2026",
  "mode": "IMPROVE",
  "checks": [
    {
      "name": "health",
      "status": "pass",
      "detail": "{\"nanobot\": \"ok\", \"vercel\": \"ok\", \"brain\": \"ok\"}",
      "time_ms": 563
    },
    {
      "name": "build",
      "status": "pass",
      "detail": "Build OK in 47.37s",
      "time_ms": 55625
    },
    {
      "name": "galileo",
      "status": "pass",
      "detail": "9/10 pass | FAIL: carica esperimento 1: missing expected [[AZIONE:loadexp]]",
      "time_ms": 147607
    },
    {
      "name": "content",
      "status": "pass",
      "detail": "62 experiments found",
      "time_ms": 3
    },
    {
      "name": "gulpease",
      "status": "pass",
      "detail": "avg=77 min=75 (target \u226560) [3 samples]",
      "time_ms": 54342
    },
    {
      "name": "browser",
      "status": "pass",
      "detail": "Title: ELAB Tutor Galileo | Simulatore Circuiti, AI Tutor e Sfide Interattive, Errors: 0",
      "time_ms": 3967
    },
    {
      "name": "ipad",
      "status": "ok",
      "detail": "Overflow: False, Small btns: 0",
      "time_ms": 2275
    }
  ],
  "checks_passed": 6,
  "checks_total": 7,
  "task_result": {
    "task": "Research-driven fix: ipad_compliance (score=0.68)",
    "status": "pending_interactive"
  },
  "research": "Scholar: 'AI tutoring scaffolding real-time' -> 5 papers\n  - [2022] Applying Real-Time Dynamic Scaffolding Techniques during Tutoring Sessions Using\n  - [2018] The Impact of Multiple Real-Time Scaffolding Experiences on Science Inquiry Prac\n  - [2018] Real-Time Scaffolding of Students\u2019 Online Data Interpretation During Inquiry wit\nKimi: Il tema 'AI tutoring scaffolding real-time' si riferisce all'uso dell'intelligenza artificiale per supportare gli studenti in modo personalizzato e in tempo reale. Ecco 3 tendenze, 1 idea e 1 rischio in questo campo.\n\n1. Tendenza 1: Personalizzazione dell'apprendimento. L'AI pu\u00f2 analizzare i progressi degli studenti e adattare il materiale di apprendimento in base alle loro esigenze personali, mig",
  "ai_scoring": null,
  "composite_score": 0.4712,
  "self_exam": null
}