{
  "cycle": 26,
  "timestamp": "2026-03-26T07:29:58.997262",
  "date": "2026-03-26",
  "time": "07:29:58 ",
  "author": "Andrea Marro \u2014 ELAB Tutor \u00a9 2026",
  "mode": "IMPROVE",
  "checks": [
    {
      "name": "health",
      "status": "pass",
      "detail": "{\"nanobot\": \"ok\", \"vercel\": \"ok\", \"brain\": \"ok\"}",
      "time_ms": 268
    },
    {
      "name": "build",
      "status": "pass",
      "detail": "Build OK in 25.71s",
      "time_ms": 29157
    },
    {
      "name": "galileo",
      "status": "pass",
      "detail": "9/10 pass | FAIL: carica esperimento 1: missing expected [[AZIONE:loadexp]]",
      "time_ms": 157946
    },
    {
      "name": "content",
      "status": "pass",
      "detail": "62 experiments found",
      "time_ms": 3
    },
    {
      "name": "gulpease",
      "status": "pass",
      "detail": "avg=77 min=71 (target \u226560) [3 samples]",
      "time_ms": 63143
    },
    {
      "name": "browser",
      "status": "pass",
      "detail": "Title: ELAB Tutor Galileo | Simulatore Circuiti, AI Tutor e Sfide Interattive, Errors: 0",
      "time_ms": 4145
    },
    {
      "name": "ipad",
      "status": "ok",
      "detail": "Overflow: False, Small btns: 0",
      "time_ms": 2245
    }
  ],
  "checks_passed": 6,
  "checks_total": 7,
  "task_result": {
    "task": "unknown",
    "status": "done",
    "output_length": 1,
    "returncode": 0,
    "lesson": "Ciclo completato (exit 0), output 1 chars. Nessun JSON strutturato prodotto."
  },
  "research": "Kimi: Gamification in STEM learning has become a popular approach to engage children in science, technology, engineering, and mathematics. This method uses game elements to make learning more interactive and enjoyable. \n\n1. Three trends in gamification for STEM learning:\n   - **Interactive Simulations**: Tools like ELAB Tutor, which simulates circuit building for children, are becoming more prevalent. T\nKimi-R: Problema 1: L'integrazione di elementi di gioco in un ambiente di apprendimento STEM pu\u00f2 risultare complesso e costoso, richiedendo tempo prezioso per la creazione e la gestione di contenuti educativi.\n\nProblema 2: La personalizzazione dell'esperienza di apprendimento per adattarsi alle diverse esigenze degli studenti pu\u00f2 essere un'impresa sfidante, poich\u00e9 richiede un'analisi dettagliata dei dati ",
  "ai_scoring": null,
  "composite_score": 0.5983,
  "self_exam": null
}